[{"name":"bat","email":"bat","phone":"bat","addr":"bat","group":"bat"},{"name":"fox","email":"fox","phone":"fox","addr":"fox","group":"fox"},{"name":"Mr. Anderson","email":"","phone":"","addr":"","group":""},{"name":"Mr.T","email":"","phone":"","addr":"","group":""},{"name":"Neo","email":"3","phone":"4","addr":"5","group":""},{"name":"Trinity","email":"","phone":"","addr":"","group":""},{"name":"a","email":"b","phone":"c","addr":"d","group":"e"},{"name":"z","email":"x","phone":"t","addr":"s","group":"v"},{"name":"1","email":"2","phone":"3","addr":"4","group":"5"},{"name":"catwoman","email":"23","phone":"243","addr":"41","group":"53"},{"name":"zzz0","email":"zzz1","phone":"zzz2","addr":"zzz3","group":"zzz4"},{"name":"dope","email":"this","phone":"totally","addr":"works","group":"!!"}]